powersimdata/__init__.py
powersimdata/data_access/__init__.py
powersimdata/data_access/context.py
powersimdata/data_access/csv_store.py
powersimdata/data_access/data_access.py
powersimdata/data_access/execute_list.py
powersimdata/data_access/execute_table.py
powersimdata/data_access/fs_helper.py
powersimdata/data_access/launcher.py
powersimdata/data_access/scenario_list.py
powersimdata/data_access/scenario_table.py
powersimdata/data_access/sql_store.py
powersimdata/data_access/ssh_fs.py
powersimdata/data_access/tests/__init__.py
powersimdata/data_access/tests/test_data_access.py
powersimdata/data_access/tests/test_execute_csv.py
powersimdata/data_access/tests/test_launcher.py
powersimdata/data_access/tests/test_scenario_csv.py
powersimdata/design/__init__.py
powersimdata/design/mimic_grid.py
powersimdata/design/scenario_info.py
powersimdata/design/compare/__init__.py
powersimdata/design/compare/generation.py
powersimdata/design/compare/helpers.py
powersimdata/design/compare/transmission.py
powersimdata/design/generation/__init__.py
powersimdata/design/generation/clean_capacity_scaling.py
powersimdata/design/generation/cost_curves.py
powersimdata/design/generation/curtailment.py
powersimdata/design/generation/tests/__init__.py
powersimdata/design/generation/tests/test_clean_capacity_scaling.py
powersimdata/design/generation/tests/test_cost_curves.py
powersimdata/design/generation/tests/test_curtailment.py
powersimdata/design/investment/__init__.py
powersimdata/design/investment/const.py
powersimdata/design/investment/create_mapping_files.py
powersimdata/design/investment/inflation.py
powersimdata/design/investment/investment_costs.py
powersimdata/design/investment/data/2020-ATB-Summary_CAPEX.csv
powersimdata/design/investment/data/LineRegMult.csv
powersimdata/design/investment/data/buses_NEEMregion.csv
powersimdata/design/investment/data/buses_ReEDS_region.csv
powersimdata/design/investment/data/reg_cap_cost_mult_default.csv
powersimdata-0.5.5.dist-info/LICENSE
powersimdata-0.5.5.dist-info/METADATA
powersimdata-0.5.5.dist-info/WHEEL
powersimdata-0.5.5.dist-info/top_level.txt
powersimdata-0.5.5.dist-info/RECORD
