Metadata-Version: 2.1
Name: powersimdata
Version: 0.5.5
Summary: Power Simulation Data
Home-page: https://github.com/Breakthrough-Energy/PowerSimData
Author: Breakthrough Energy
Author-email: sciences@breakthroughenergy.org
Project-URL: Bug Tracker, https://github.com/Breakthrough-Energy/PowerSimData/issues
Classifier: License :: OSI Approved :: MIT License
Classifier: Operating System :: OS Independent
Classifier: Programming Language :: Python :: 3
Classifier: Programming Language :: Python :: 3.8
Classifier: Programming Language :: Python :: 3.9
Classifier: Programming Language :: Python :: 3.10
Requires-Python: >=3.8
License-File: LICENSE
Requires-Dist: networkx
Requires-Dist: numpy
Requires-Dist: pandas
Requires-Dist: paramiko
Requires-Dist: scipy
Requires-Dist: tqdm
Requires-Dist: requests
Requires-Dist: fs (==2.4.14)
Requires-Dist: fs.sshfs
Requires-Dist: fs-azureblob (>=0.2.1)
Requires-Dist: pypsa
